hypothesis/__init__.py
hypothesis/hypothesis.py
hypothesis_api-1.0.2.dist-info/LICENSE
hypothesis_api-1.0.2.dist-info/METADATA
hypothesis_api-1.0.2.dist-info/WHEEL
hypothesis_api-1.0.2.dist-info/top_level.txt
hypothesis_api-1.0.2.dist-info/RECORD
