Metadata-Version: 2.1
Name: hypothesis-api
Version: 1.0.2
Summary: Python wrapper for the Hypothesis annotation system
Home-page: https://github.com/judell/hypothesis
Author: Jon Udell
Author-email: judell@hypothes.is
License: UNKNOWN
Platform: UNKNOWN
Classifier: Programming Language :: Python :: 3
Classifier: License :: OSI Approved :: MIT License
Classifier: Operating System :: OS Independent
Requires-Python: >=3.6
License-File: LICENSE
